gppt/__init__.py
gppt/auth.py
gppt/consts.py
gppt/gppt.py
gppt/main.py
gppt/model_types.py
gppt/py.typed
gppt/utils.py
gppt-4.2.0.dist-info/METADATA
gppt-4.2.0.dist-info/WHEEL
gppt-4.2.0.dist-info/entry_points.txt
gppt-4.2.0.dist-info/licenses/LICENSE.txt
gppt-4.2.0.dist-info/RECORD
