Metadata-Version: 2.4
Name: gppt
Version: 4.2.0
Summary: Get your Pixiv token (for running upbit/pixivpy)
Project-URL: Repository, https://github.com/eggplants/get-pixivpy-token
Author-email: eggplants <w10776e8w@yahoo.co.jp>
License: MIT
License-File: LICENSE.txt
Keywords: api,pixiv,token
Classifier: License :: OSI Approved :: MIT License
Classifier: Programming Language :: Python
Classifier: Programming Language :: Python :: 3 :: Only
Classifier: Programming Language :: Python :: 3.10
Classifier: Programming Language :: Python :: 3.11
Classifier: Programming Language :: Python :: 3.12
Classifier: Programming Language :: Python :: 3.13
Classifier: Programming Language :: Python :: 3.14
Classifier: Programming Language :: Python :: Implementation :: CPython
Classifier: Typing :: Typed
Requires-Python: <4,>=3.10
Requires-Dist: install-playwright>=0.1.1
Requires-Dist: pixivpy3<4,>=3.7.5
Requires-Dist: playwright>=1.57
Requires-Dist: pwinput<2,>=1.0.3
Requires-Dist: requests<3,>=2.32.3
